fancyInput/__init__.py
fancyInput/option.py
fancyInput/asker/__init__.py
fancyInput/asker/asker.py
fancyInput/baseComponents/__init__.py
fancyInput/baseComponents/alignedPanel.py
fancyInput/exp/__init__.py
fancyInput/exp/exceptions.py
fancyInput/groups/__init__.py
fancyInput/groups/option.py
fancyInput/groups/optionGroup.py
fancyInput/optionGroup/__init__.py
fancyInput/optionGroup/horizontalOptionGroup.py
fancyInput/optionGroup/optionGroup.py
fancyInput/optionGroup/verticalOptionGroup.py
module/__init__.py
module/option.py
fancyInput-0.0.21.dist-info/LICENSE
fancyInput-0.0.21.dist-info/METADATA
fancyInput-0.0.21.dist-info/WHEEL
fancyInput-0.0.21.dist-info/top_level.txt
fancyInput-0.0.21.dist-info/RECORD
