Metadata-Version: 2.1
Name: fancyInput
Version: 0.0.21
Summary: A terminal-based python input tool for asking users with several options and except their input.
Home-page: https://github.com/MintCoffeeCat/FancyInput
Author: MintCoffeeCat
Author-email: zzwyxl@163.com
Classifier: Programming Language :: Python :: 3
Classifier: License :: OSI Approved :: MIT License
Classifier: Operating System :: OS Independent
License-File: LICENSE
Requires-Dist: rich
Requires-Dist: wcwidth
